Metadata-Version: 2.1
Name: git-cloner
Version: 0.0.4
Summary: Batch clone projects from GitLab server
Home-page: https://github.com/gebing/git-cloner
Author: gebing
Author-email: gebing@foxmail.com
License: Apache License 2.0
Keywords: git clone
Platform: any
Classifier: Development Status :: 3 - Alpha
Classifier: License :: OSI Approved :: Apache Software License
Classifier: Programming Language :: Python :: 2.7
Classifier: Programming Language :: Python :: 3.5
Classifier: Programming Language :: Python :: 3.6
Classifier: Programming Language :: Python :: 3.7
Classifier: Topic :: System :: Distributed Computing
Classifier: Topic :: System :: Networking
